hartmann/__init__.py
hartmann/__main__.py
hartmann/actor/__init__.py
hartmann/actor/actor.py
hartmann/actor/commands.py
hartmann/calibration.py
hartmann/etc/hartmann.yml
hartmann/etc/schema.json
hartmann/exceptions.py
hartmann/hartmann.py
sdss_hartmannactor-3.0.0.dist-info/METADATA
sdss_hartmannactor-3.0.0.dist-info/WHEEL
sdss_hartmannactor-3.0.0.dist-info/entry_points.txt
sdss_hartmannactor-3.0.0.dist-info/RECORD
